abcvoting/__init__.py
abcvoting/abcrules.py
abcvoting/abcrules_gurobi.py
abcvoting/abcrules_mip.py
abcvoting/abcrules_ortools.py
abcvoting/abcrules_pulp.py
abcvoting/fileio.py
abcvoting/generate.py
abcvoting/misc.py
abcvoting/output.py
abcvoting/preferences.py
abcvoting/properties.py
abcvoting/scores.py
abcvoting-2.15.0.dist-info/licenses/LICENSE
abcvoting-2.15.0.dist-info/METADATA
abcvoting-2.15.0.dist-info/WHEEL
abcvoting-2.15.0.dist-info/top_level.txt
abcvoting-2.15.0.dist-info/RECORD
