Metadata-Version: 2.4
Name: abcvoting
Version: 2.15.0
Summary: A Python library of approval-based committee (ABC) rules
Home-page: https://github.com/martinlackner/abcvoting/
Author: Martin Lackner
Author-email: unexpected@sent.at
License: MIT License
Project-URL: Bug Tracker, https://github.com/martinlackner/abcvoting/issues
Classifier: Programming Language :: Python :: 3
Classifier: Programming Language :: Python :: 3.9
Classifier: Programming Language :: Python :: 3.10
Classifier: Programming Language :: Python :: 3.11
Classifier: Programming Language :: Python :: 3.12
Classifier: Programming Language :: Python :: 3.13
Classifier: License :: OSI Approved :: MIT License
Classifier: Operating System :: OS Independent
Classifier: Intended Audience :: Science/Research
Requires-Python: >=3.8
License-File: LICENSE
Requires-Dist: networkx[default]>=2.6.3
Requires-Dist: ruamel.yaml>=0.17
Requires-Dist: numpy>=1.21
Requires-Dist: gurobipy>=11.0
Requires-Dist: preflibtools>=2.0.12
Requires-Dist: prefsampling>=0.1.19
Requires-Dist: pabutools>=1.1.15
Requires-Dist: pulp[open_py]>=3.2
Provides-Extra: dev
Requires-Dist: pytest>=6; extra == "dev"
Requires-Dist: coverage[toml]>=5.3; extra == "dev"
Requires-Dist: black==25.1; extra == "dev"
Requires-Dist: Sphinx>=7.0; extra == "dev"
Requires-Dist: sphinx-rtd-theme>=1.0.0; extra == "dev"
Requires-Dist: numpydoc>=1.5; extra == "dev"
Requires-Dist: sphinx-codeautolink>=0.15; extra == "dev"
Requires-Dist: matplotlib>=3.4.3; extra == "dev"
Dynamic: author
Dynamic: author-email
Dynamic: classifier
Dynamic: description
Dynamic: description-content-type
Dynamic: home-page
Dynamic: license
Dynamic: license-file
Dynamic: project-url
Dynamic: provides-extra
Dynamic: requires-dist
Dynamic: requires-python
Dynamic: summary
